{"Pq/BP+Tcv8t5Bv4aBqMcVg==":"me%20with%20hololens-122x123.jpg","RhlPcH4ry5js/9QTg2JBcQ==":"profile_pic-637x960.jpg","W8Acn+zaW+MvJqAlWWGrHg==":"sunset-590x443.jpg","JfHwBqkO49InT9rK5WXthg==":"password-310x163.jpg","nhbD3z73Ta0BJzC7twBiOQ==":"sunset-960x720.jpg","/9ERXiMvMr1KGAEo/P6EiQ==":"background5.jpg","CGGtf1MuvLFB/KUrA/+mag==":"jumbotron.jpg","bN9TuD1cCe1ShF/c3/b0Qg==":"jumbotron2.jpg","9pJ3S0b/sS5BygnehuczDw==":"mbr-1080x720.jpg","hsvPkLncMA0+ps+pXC4GqA==":"mbr-1200x848.jpg","93BdeSebGsTVg2st7F0rwA==":"mbr-1-1080x720.jpg","HLpslKm/JaC1S0xfv6Kp8g==":"treepng-227x222.png","2kBbLe2DfOwSWuV9gaeGZw==":"dit12-600x331.png","XrYdyZ0smBt0E6yR45hFKA==":"tree-command-linux-hierarchical-structure-directory-tree-500x617.png"}